vidfetch_bot/__init__.py
vidfetch_bot/__main__.py
vidfetch_bot/bot.py
vidfetch_bot/filters.py
vidfetch_bot/handlers.py
vidfetch_bot/utils.py
vidfetch_bot/video.py
vidfetch_bot-0.4.4.dist-info/licenses/LICENSE
vidfetch_bot-0.4.4.dist-info/METADATA
vidfetch_bot-0.4.4.dist-info/WHEEL
vidfetch_bot-0.4.4.dist-info/top_level.txt
vidfetch_bot-0.4.4.dist-info/RECORD
