Metadata-Version: 2.4
Name: vidfetch_bot
Version: 0.4.4
Summary: This bot watches messages for URLs then passes those to yt-dlp for processing and download. It then replies to the message containing the URL with the video embedded.
Author-email: Arthur Tucker <firm.pin7067@fastmail.com>
License-Expression: GPL-3.0
Project-URL: Homepage, https://github.com/arthurlt/vidfetch_bot
Project-URL: Issues, https://github.com/arthurlt/vidfetch_bot/issues
Keywords: TikTok,Instagram,YouTube,Telegram
Classifier: Development Status :: 4 - Beta
Classifier: Environment :: No Input/Output (Daemon)
Classifier: Natural Language :: English
Classifier: Programming Language :: Python :: 3
Classifier: Programming Language :: Python :: 3.11
Classifier: Programming Language :: Python :: 3.12
Classifier: Programming Language :: Python :: 3.13
Classifier: Operating System :: OS Independent
Classifier: Topic :: Communications :: Chat
Classifier: Topic :: Multimedia :: Sound/Audio :: Conversion
Requires-Python: >=3.11
License-File: LICENSE
Requires-Dist: aiogram~=3.2
Requires-Dist: yt-dlp
Dynamic: license-file
